site24x7/__init__.py
site24x7/main.py
site24x7/connector/__init__.py
site24x7/connector/cache_client.py
site24x7/connector/database_client.py
site24x7/connector/redis_client.py
site24x7/connector/request_client.py
site24x7/connector/models/__init__.py
site24x7/connector/models/model.py
site24x7/utils/__init__.py
site24x7/utils/util.py
site24x7/utils/zoho.py
site24x7_plugin_helper/__init__.py
site24x7_plugin_helper/main.py
site24x7_plugin_helper/connector/__init__.py
site24x7_plugin_helper/connector/cache_client.py
site24x7_plugin_helper/connector/database_client.py
site24x7_plugin_helper/connector/redis_client.py
site24x7_plugin_helper/connector/request_client.py
site24x7_plugin_helper/connector/models/__init__.py
site24x7_plugin_helper/connector/models/model.py
site24x7_plugin_helper/utils/__init__.py
site24x7_plugin_helper/utils/util.py
site24x7_plugin_helper/utils/zoho.py
site24x7-0.8.3.dist-info/LICENSE
site24x7-0.8.3.dist-info/METADATA
site24x7-0.8.3.dist-info/WHEEL
site24x7-0.8.3.dist-info/top_level.txt
site24x7-0.8.3.dist-info/RECORD
