Metadata-Version: 2.1
Name: site24x7
Version: 0.8.3
Summary: plugin integration and zoho authentication 2.0 tool
Author-email: Renas Mirkan Kilic <mirkanbaba1@gmail.com>
License: Copyright (c) 2018 The Python Packaging Authority
Project-URL: Homepage, https://github.com/mirkan1/site24x7
Project-URL: Bug Tracker, https://github.com/mirkan1/site24x7/issues
Classifier: Programming Language :: Python :: 3
Classifier: License :: OSI Approved :: MIT License
Classifier: Operating System :: OS Independent
Requires-Python: >=3.6
License-File: LICENSE
